{
  "item": [
    {
      "id": "c18c6ec8-7b5f-4eae-a5f6-e27157d41d18",
      "name": "Identity Providers",
      "description": {
        "content": "Configure and manage external identity providers for federated login.",
        "type": "text/plain"
      },
      "item": [
        {
          "id": "9dfd804b-4ff6-4a53-a086-345e0ca7bb9d",
          "name": "List identity providers",
          "request": {
            "name": "List identity providers",
            "description": {},
            "url": {
              "path": [
                "identity-providers"
              ],
              "host": [
                "{{baseUrl}}"
              ],
              "query": [],
              "variable": [
                {
                  "description": {
                    "content": "",
                    "type": "text/plain"
                  },
                  "type": "any",
                  "value": "{{host}}",
                  "key": "host"
                },
                {
                  "description": {
                    "content": "",
                    "type": "text/plain"
                  },
                  "type": "any",
                  "value": "{{port}}",
                  "key": "port"
                }
              ]
            },
            "header": [
              {
                "key": "Accept",
                "value": "application/json"
              }
            ],
            "method": "GET",
            "auth": null
          },
          "response": [
            {
              "id": "d6300a11-250a-4c21-8ba6-60c5a7143751",
              "name": "List of identity providers",
              "originalRequest": {
                "url": {
                  "path": [
                    "identity-providers"
                  ],
                  "host": [
                    "{{baseUrl}}"
                  ],
                  "query": [],
                  "variable": [
                    {
                      "description": {
                        "content": "",
                        "type": "text/plain"
                      },
                      "type": "any",
                      "value": "{{host}}",
                      "key": "host"
                    },
                    {
                      "description": {
                        "content": "",
                        "type": "text/plain"
                      },
                      "type": "any",
                      "value": "{{port}}",
                      "key": "port"
                    }
                  ]
                },
                "header": [
                  {
                    "description": {
                      "content": "Added as a part of security scheme: oauth2",
                      "type": "text/plain"
                    },
                    "key": "Authorization",
                    "value": "<token>"
                  },
                  {
                    "key": "Accept",
                    "value": "application/json"
                  }
                ],
                "method": "GET",
                "body": {}
              },
              "status": "OK",
              "code": 200,
              "header": [
                {
                  "key": "Content-Type",
                  "value": "application/json"
                }
              ],
              "body": "[\n  {\n    \"id\": \"<uuid>\",\n    \"name\": \"<string>\",\n    \"type\": \"<string>\",\n    \"isReadOnly\": \"<boolean>\",\n    \"description\": \"<string>\"\n  },\n  {\n    \"id\": \"<uuid>\",\n    \"name\": \"<string>\",\n    \"type\": \"<string>\",\n    \"isReadOnly\": \"<boolean>\",\n    \"description\": \"<string>\"\n  }\n]",
              "cookie": [],
              "_postman_previewlanguage": "json"
            },
            {
              "id": "edc99e0e-2987-4b72-9ead-fef572b2024f",
              "name": "Bad request",
              "originalRequest": {
                "url": {
                  "path": [
                    "identity-providers"
                  ],
                  "host": [
                    "{{baseUrl}}"
                  ],
                  "query": [],
                  "variable": [
                    {
                      "description": {
                        "content": "",
                        "type": "text/plain"
                      },
                      "type": "any",
                      "value": "{{host}}",
                      "key": "host"
                    },
                    {
                      "description": {
                        "content": "",
                        "type": "text/plain"
                      },
                      "type": "any",
                      "value": "{{port}}",
                      "key": "port"
                    }
                  ]
                },
                "header": [
                  {
                    "description": {
                      "content": "Added as a part of security scheme: oauth2",
                      "type": "text/plain"
                    },
                    "key": "Authorization",
                    "value": "<token>"
                  },
                  {
                    "key": "Accept",
                    "value": "application/json"
                  }
                ],
                "method": "GET",
                "body": {}
              },
              "status": "Bad Request",
              "code": 400,
              "header": [
                {
                  "key": "Content-Type",
                  "value": "application/json"
                }
              ],
              "body": "{\n  \"code\": \"<string>\",\n  \"message\": {\n    \"key\": \"<string>\",\n    \"defaultValue\": \"<string>\"\n  },\n  \"description\": {\n    \"key\": \"<string>\",\n    \"defaultValue\": \"<string>\"\n  }\n}",
              "cookie": [],
              "_postman_previewlanguage": "json"
            },
            {
              "id": "45fb3ae5-5c9d-4734-92d0-5d81f46d00c8",
              "name": "Internal server error",
              "originalRequest": {
                "url": {
                  "path": [
                    "identity-providers"
                  ],
                  "host": [
                    "{{baseUrl}}"
                  ],
                  "query": [],
                  "variable": [
                    {
                      "description": {
                        "content": "",
                        "type": "text/plain"
                      },
                      "type": "any",
                      "value": "{{host}}",
                      "key": "host"
                    },
                    {
                      "description": {
                        "content": "",
                        "type": "text/plain"
                      },
                      "type": "any",
                      "value": "{{port}}",
                      "key": "port"
                    }
                  ]
                },
                "header": [
                  {
                    "description": {
                      "content": "Added as a part of security scheme: oauth2",
                      "type": "text/plain"
                    },
                    "key": "Authorization",
                    "value": "<token>"
                  }
                ],
                "method": "GET",
                "body": {}
              },
              "status": "Internal Server Error",
              "code": 500,
              "header": [
                {
                  "key": "Content-Type",
                  "value": "text/plain"
                }
              ],
              "body": "",
              "cookie": [],
              "_postman_previewlanguage": "text"
            }
          ],
          "event": [],
          "protocolProfileBehavior": {
            "disableBodyPruning": true
          }
        },
        {
          "id": "edc94da2-5a0f-499a-b3a4-42ab5d26ea8e",
          "name": "Create an identity provider",
          "request": {
            "name": "Create an identity provider",
            "description": {},
            "url": {
              "path": [
                "identity-providers"
              ],
              "host": [
                "{{baseUrl}}"
              ],
              "query": [],
              "variable": [
                {
                  "description": {
                    "content": "",
                    "type": "text/plain"
                  },
                  "type": "any",
                  "value": "{{host}}",
                  "key": "host"
                },
                {
                  "description": {
                    "content": "",
                    "type": "text/plain"
                  },
                  "type": "any",
                  "value": "{{port}}",
                  "key": "port"
                }
              ]
            },
            "header": [
              {
                "key": "Content-Type",
                "value": "application/json"
              },
              {
                "key": "Accept",
                "value": "application/json"
              }
            ],
            "method": "POST",
            "auth": null,
            "body": {
              "mode": "raw",
              "raw": "{\n  \"name\": \"<string>\",\n  \"type\": \"<string>\",\n  \"description\": \"<string>\",\n  \"properties\": [\n    {\n      \"name\": \"<string>\",\n      \"value\": \"<string>\",\n      \"isSecret\": \"<boolean>\"\n    },\n    {\n      \"name\": \"<string>\",\n      \"value\": \"<string>\",\n      \"isSecret\": \"<boolean>\"\n    }\n  ]\n}",
              "options": {
                "raw": {
                  "language": "json"
                }
              }
            }
          },
          "response": [
            {
              "id": "f5a247ab-662f-437f-afe0-0c93254e2351",
              "name": "Identity provider created",
              "originalRequest": {
                "url": {
                  "path": [
                    "identity-providers"
                  ],
                  "host": [
                    "{{baseUrl}}"
                  ],
                  "query": [],
                  "variable": [
                    {
                      "description": {
                        "content": "",
                        "type": "text/plain"
                      },
                      "type": "any",
                      "value": "{{host}}",
                      "key": "host"
                    },
                    {
                      "description": {
                        "content": "",
                        "type": "text/plain"
                      },
                      "type": "any",
                      "value": "{{port}}",
                      "key": "port"
                    }
                  ]
                },
                "header": [
                  {
                    "description": {
                      "content": "Added as a part of security scheme: oauth2",
                      "type": "text/plain"
                    },
                    "key": "Authorization",
                    "value": "<token>"
                  },
                  {
                    "key": "Accept",
                    "value": "application/json"
                  }
                ],
                "method": "POST",
                "body": {
                  "mode": "raw",
                  "raw": "{\n  \"name\": \"<string>\",\n  \"type\": \"<string>\",\n  \"description\": \"<string>\",\n  \"properties\": [\n    {\n      \"name\": \"<string>\",\n      \"value\": \"<string>\",\n      \"isSecret\": \"<boolean>\"\n    },\n    {\n      \"name\": \"<string>\",\n      \"value\": \"<string>\",\n      \"isSecret\": \"<boolean>\"\n    }\n  ]\n}",
                  "options": {
                    "raw": {
                      "language": "json"
                    }
                  }
                }
              },
              "status": "Created",
              "code": 201,
              "header": [
                {
                  "key": "Content-Type",
                  "value": "application/json"
                }
              ],
              "body": "{\n  \"id\": \"<uuid>\",\n  \"name\": \"<string>\",\n  \"type\": \"<string>\",\n  \"description\": \"<string>\",\n  \"properties\": [\n    {\n      \"name\": \"<string>\",\n      \"value\": \"<string>\",\n      \"isSecret\": \"<boolean>\"\n    },\n    {\n      \"name\": \"<string>\",\n      \"value\": \"<string>\",\n      \"isSecret\": \"<boolean>\"\n    }\n  ]\n}",
              "cookie": [],
              "_postman_previewlanguage": "json"
            },
            {
              "id": "2404966f-9bb9-4f95-b996-2734e3268d16",
              "name": "Bad request",
              "originalRequest": {
                "url": {
                  "path": [
                    "identity-providers"
                  ],
                  "host": [
                    "{{baseUrl}}"
                  ],
                  "query": [],
                  "variable": [
                    {
                      "description": {
                        "content": "",
                        "type": "text/plain"
                      },
                      "type": "any",
                      "value": "{{host}}",
                      "key": "host"
                    },
                    {
                      "description": {
                        "content": "",
                        "type": "text/plain"
                      },
                      "type": "any",
                      "value": "{{port}}",
                      "key": "port"
                    }
                  ]
                },
                "header": [
                  {
                    "description": {
                      "content": "Added as a part of security scheme: oauth2",
                      "type": "text/plain"
                    },
                    "key": "Authorization",
                    "value": "<token>"
                  },
                  {
                    "key": "Accept",
                    "value": "application/json"
                  }
                ],
                "method": "POST",
                "body": {
                  "mode": "raw",
                  "raw": "{\n  \"name\": \"<string>\",\n  \"type\": \"<string>\",\n  \"description\": \"<string>\",\n  \"properties\": [\n    {\n      \"name\": \"<string>\",\n      \"value\": \"<string>\",\n      \"isSecret\": \"<boolean>\"\n    },\n    {\n      \"name\": \"<string>\",\n      \"value\": \"<string>\",\n      \"isSecret\": \"<boolean>\"\n    }\n  ]\n}",
                  "options": {
                    "raw": {
                      "language": "json"
                    }
                  }
                }
              },
              "status": "Bad Request",
              "code": 400,
              "header": [
                {
                  "key": "Content-Type",
                  "value": "application/json"
                }
              ],
              "body": "{\n  \"code\": \"<string>\",\n  \"message\": {\n    \"key\": \"<string>\",\n    \"defaultValue\": \"<string>\"\n  },\n  \"description\": {\n    \"key\": \"<string>\",\n    \"defaultValue\": \"<string>\"\n  }\n}",
              "cookie": [],
              "_postman_previewlanguage": "json"
            },
            {
              "id": "17acf840-d8d1-4c47-9adb-aba5e21d0345",
              "name": "Conflict",
              "originalRequest": {
                "url": {
                  "path": [
                    "identity-providers"
                  ],
                  "host": [
                    "{{baseUrl}}"
                  ],
                  "query": [],
                  "variable": [
                    {
                      "description": {
                        "content": "",
                        "type": "text/plain"
                      },
                      "type": "any",
                      "value": "{{host}}",
                      "key": "host"
                    },
                    {
                      "description": {
                        "content": "",
                        "type": "text/plain"
                      },
                      "type": "any",
                      "value": "{{port}}",
                      "key": "port"
                    }
                  ]
                },
                "header": [
                  {
                    "description": {
                      "content": "Added as a part of security scheme: oauth2",
                      "type": "text/plain"
                    },
                    "key": "Authorization",
                    "value": "<token>"
                  },
                  {
                    "key": "Accept",
                    "value": "application/json"
                  }
                ],
                "method": "POST",
                "body": {
                  "mode": "raw",
                  "raw": "{\n  \"name\": \"<string>\",\n  \"type\": \"<string>\",\n  \"description\": \"<string>\",\n  \"properties\": [\n    {\n      \"name\": \"<string>\",\n      \"value\": \"<string>\",\n      \"isSecret\": \"<boolean>\"\n    },\n    {\n      \"name\": \"<string>\",\n      \"value\": \"<string>\",\n      \"isSecret\": \"<boolean>\"\n    }\n  ]\n}",
                  "options": {
                    "raw": {
                      "language": "json"
                    }
                  }
                }
              },
              "status": "Conflict",
              "code": 409,
              "header": [
                {
                  "key": "Content-Type",
                  "value": "application/json"
                }
              ],
              "body": "{\n  \"code\": \"<string>\",\n  \"message\": {\n    \"key\": \"<string>\",\n    \"defaultValue\": \"<string>\"\n  },\n  \"description\": {\n    \"key\": \"<string>\",\n    \"defaultValue\": \"<string>\"\n  }\n}",
              "cookie": [],
              "_postman_previewlanguage": "json"
            },
            {
              "id": "3308052a-3bca-444d-bd7d-bfe1d32cccc7",
              "name": "Internal server error",
              "originalRequest": {
                "url": {
                  "path": [
                    "identity-providers"
                  ],
                  "host": [
                    "{{baseUrl}}"
                  ],
                  "query": [],
                  "variable": [
                    {
                      "description": {
                        "content": "",
                        "type": "text/plain"
                      },
                      "type": "any",
                      "value": "{{host}}",
                      "key": "host"
                    },
                    {
                      "description": {
                        "content": "",
                        "type": "text/plain"
                      },
                      "type": "any",
                      "value": "{{port}}",
                      "key": "port"
                    }
                  ]
                },
                "header": [
                  {
                    "description": {
                      "content": "Added as a part of security scheme: oauth2",
                      "type": "text/plain"
                    },
                    "key": "Authorization",
                    "value": "<token>"
                  }
                ],
                "method": "POST",
                "body": {
                  "mode": "raw",
                  "raw": "{\n  \"name\": \"<string>\",\n  \"type\": \"<string>\",\n  \"description\": \"<string>\",\n  \"properties\": [\n    {\n      \"name\": \"<string>\",\n      \"value\": \"<string>\",\n      \"isSecret\": \"<boolean>\"\n    },\n    {\n      \"name\": \"<string>\",\n      \"value\": \"<string>\",\n      \"isSecret\": \"<boolean>\"\n    }\n  ]\n}",
                  "options": {
                    "raw": {
                      "language": "json"
                    }
                  }
                }
              },
              "status": "Internal Server Error",
              "code": 500,
              "header": [
                {
                  "key": "Content-Type",
                  "value": "text/plain"
                }
              ],
              "body": "",
              "cookie": [],
              "_postman_previewlanguage": "text"
            }
          ],
          "event": [],
          "protocolProfileBehavior": {
            "disableBodyPruning": true
          }
        },
        {
          "id": "6494cc66-6829-40f2-8340-9c29ab9544d4",
          "name": "Get an identity provider by ID",
          "request": {
            "name": "Get an identity provider by ID",
            "description": {},
            "url": {
              "path": [
                "identity-providers",
                ":id"
              ],
              "host": [
                "{{baseUrl}}"
              ],
              "query": [],
              "variable": [
                {
                  "disabled": false,
                  "type": "any",
                  "value": "<uuid>",
                  "key": "id",
                  "description": "(Required) "
                },
                {
                  "description": {
                    "content": "",
                    "type": "text/plain"
                  },
                  "type": "any",
                  "value": "{{host}}",
                  "key": "host"
                },
                {
                  "description": {
                    "content": "",
                    "type": "text/plain"
                  },
                  "type": "any",
                  "value": "{{port}}",
                  "key": "port"
                }
              ]
            },
            "header": [
              {
                "key": "Accept",
                "value": "application/json"
              }
            ],
            "method": "GET",
            "auth": null
          },
          "response": [
            {
              "id": "bd06e9a4-b5af-4afa-8f27-8eaa6013b9b0",
              "name": "Identity provider details",
              "originalRequest": {
                "url": {
                  "path": [
                    "identity-providers",
                    ":id"
                  ],
                  "host": [
                    "{{baseUrl}}"
                  ],
                  "query": [],
                  "variable": [
                    {
                      "disabled": false,
                      "type": "any",
                      "value": "<uuid>",
                      "key": "id",
                      "description": "(Required) "
                    },
                    {
                      "description": {
                        "content": "",
                        "type": "text/plain"
                      },
                      "type": "any",
                      "value": "{{host}}",
                      "key": "host"
                    },
                    {
                      "description": {
                        "content": "",
                        "type": "text/plain"
                      },
                      "type": "any",
                      "value": "{{port}}",
                      "key": "port"
                    }
                  ]
                },
                "header": [
                  {
                    "description": {
                      "content": "Added as a part of security scheme: oauth2",
                      "type": "text/plain"
                    },
                    "key": "Authorization",
                    "value": "<token>"
                  },
                  {
                    "key": "Accept",
                    "value": "application/json"
                  }
                ],
                "method": "GET",
                "body": {}
              },
              "status": "OK",
              "code": 200,
              "header": [
                {
                  "key": "Content-Type",
                  "value": "application/json"
                }
              ],
              "body": "{\n  \"id\": \"<uuid>\",\n  \"name\": \"<string>\",\n  \"type\": \"<string>\",\n  \"description\": \"<string>\",\n  \"properties\": [\n    {\n      \"name\": \"<string>\",\n      \"value\": \"<string>\",\n      \"isSecret\": \"<boolean>\"\n    },\n    {\n      \"name\": \"<string>\",\n      \"value\": \"<string>\",\n      \"isSecret\": \"<boolean>\"\n    }\n  ]\n}",
              "cookie": [],
              "_postman_previewlanguage": "json"
            },
            {
              "id": "997c2563-135e-4ee4-bc22-7d96f5e9e4d9",
              "name": "Bad request",
              "originalRequest": {
                "url": {
                  "path": [
                    "identity-providers",
                    ":id"
                  ],
                  "host": [
                    "{{baseUrl}}"
                  ],
                  "query": [],
                  "variable": [
                    {
                      "disabled": false,
                      "type": "any",
                      "value": "<uuid>",
                      "key": "id",
                      "description": "(Required) "
                    },
                    {
                      "description": {
                        "content": "",
                        "type": "text/plain"
                      },
                      "type": "any",
                      "value": "{{host}}",
                      "key": "host"
                    },
                    {
                      "description": {
                        "content": "",
                        "type": "text/plain"
                      },
                      "type": "any",
                      "value": "{{port}}",
                      "key": "port"
                    }
                  ]
                },
                "header": [
                  {
                    "description": {
                      "content": "Added as a part of security scheme: oauth2",
                      "type": "text/plain"
                    },
                    "key": "Authorization",
                    "value": "<token>"
                  },
                  {
                    "key": "Accept",
                    "value": "application/json"
                  }
                ],
                "method": "GET",
                "body": {}
              },
              "status": "Bad Request",
              "code": 400,
              "header": [
                {
                  "key": "Content-Type",
                  "value": "application/json"
                }
              ],
              "body": "{\n  \"code\": \"<string>\",\n  \"message\": {\n    \"key\": \"<string>\",\n    \"defaultValue\": \"<string>\"\n  },\n  \"description\": {\n    \"key\": \"<string>\",\n    \"defaultValue\": \"<string>\"\n  }\n}",
              "cookie": [],
              "_postman_previewlanguage": "json"
            },
            {
              "id": "7b51f886-f33e-4bac-bd30-48712c380b21",
              "name": "Identity provider not found",
              "originalRequest": {
                "url": {
                  "path": [
                    "identity-providers",
                    ":id"
                  ],
                  "host": [
                    "{{baseUrl}}"
                  ],
                  "query": [],
                  "variable": [
                    {
                      "disabled": false,
                      "type": "any",
                      "value": "<uuid>",
                      "key": "id",
                      "description": "(Required) "
                    },
                    {
                      "description": {
                        "content": "",
                        "type": "text/plain"
                      },
                      "type": "any",
                      "value": "{{host}}",
                      "key": "host"
                    },
                    {
                      "description": {
                        "content": "",
                        "type": "text/plain"
                      },
                      "type": "any",
                      "value": "{{port}}",
                      "key": "port"
                    }
                  ]
                },
                "header": [
                  {
                    "description": {
                      "content": "Added as a part of security scheme: oauth2",
                      "type": "text/plain"
                    },
                    "key": "Authorization",
                    "value": "<token>"
                  },
                  {
                    "key": "Accept",
                    "value": "application/json"
                  }
                ],
                "method": "GET",
                "body": {}
              },
              "status": "Not Found",
              "code": 404,
              "header": [
                {
                  "key": "Content-Type",
                  "value": "application/json"
                }
              ],
              "body": "{\n  \"code\": \"<string>\",\n  \"message\": {\n    \"key\": \"<string>\",\n    \"defaultValue\": \"<string>\"\n  },\n  \"description\": {\n    \"key\": \"<string>\",\n    \"defaultValue\": \"<string>\"\n  }\n}",
              "cookie": [],
              "_postman_previewlanguage": "json"
            },
            {
              "id": "843c20b8-5a31-4518-b5ee-e0193c8cdeac",
              "name": "Internal server error",
              "originalRequest": {
                "url": {
                  "path": [
                    "identity-providers",
                    ":id"
                  ],
                  "host": [
                    "{{baseUrl}}"
                  ],
                  "query": [],
                  "variable": [
                    {
                      "disabled": false,
                      "type": "any",
                      "value": "<uuid>",
                      "key": "id",
                      "description": "(Required) "
                    },
                    {
                      "description": {
                        "content": "",
                        "type": "text/plain"
                      },
                      "type": "any",
                      "value": "{{host}}",
                      "key": "host"
                    },
                    {
                      "description": {
                        "content": "",
                        "type": "text/plain"
                      },
                      "type": "any",
                      "value": "{{port}}",
                      "key": "port"
                    }
                  ]
                },
                "header": [
                  {
                    "description": {
                      "content": "Added as a part of security scheme: oauth2",
                      "type": "text/plain"
                    },
                    "key": "Authorization",
                    "value": "<token>"
                  }
                ],
                "method": "GET",
                "body": {}
              },
              "status": "Internal Server Error",
              "code": 500,
              "header": [
                {
                  "key": "Content-Type",
                  "value": "text/plain"
                }
              ],
              "body": "",
              "cookie": [],
              "_postman_previewlanguage": "text"
            }
          ],
          "event": [],
          "protocolProfileBehavior": {
            "disableBodyPruning": true
          }
        },
        {
          "id": "fcdcfb05-7907-4475-a930-545c6714b37f",
          "name": "Update an identity provider",
          "request": {
            "name": "Update an identity provider",
            "description": {},
            "url": {
              "path": [
                "identity-providers",
                ":id"
              ],
              "host": [
                "{{baseUrl}}"
              ],
              "query": [],
              "variable": [
                {
                  "disabled": false,
                  "type": "any",
                  "value": "<uuid>",
                  "key": "id",
                  "description": "(Required) "
                },
                {
                  "description": {
                    "content": "",
                    "type": "text/plain"
                  },
                  "type": "any",
                  "value": "{{host}}",
                  "key": "host"
                },
                {
                  "description": {
                    "content": "",
                    "type": "text/plain"
                  },
                  "type": "any",
                  "value": "{{port}}",
                  "key": "port"
                }
              ]
            },
            "header": [
              {
                "key": "Content-Type",
                "value": "application/json"
              },
              {
                "key": "Accept",
                "value": "application/json"
              }
            ],
            "method": "PUT",
            "auth": null,
            "body": {
              "mode": "raw",
              "raw": "{\n  \"name\": \"<string>\",\n  \"type\": \"<string>\",\n  \"description\": \"<string>\",\n  \"properties\": [\n    {\n      \"name\": \"<string>\",\n      \"value\": \"<string>\",\n      \"isSecret\": \"<boolean>\"\n    },\n    {\n      \"name\": \"<string>\",\n      \"value\": \"<string>\",\n      \"isSecret\": \"<boolean>\"\n    }\n  ]\n}",
              "options": {
                "raw": {
                  "language": "json"
                }
              }
            }
          },
          "response": [
            {
              "id": "dad900e8-2333-4838-8472-aacd23937492",
              "name": "Identity provider updated",
              "originalRequest": {
                "url": {
                  "path": [
                    "identity-providers",
                    ":id"
                  ],
                  "host": [
                    "{{baseUrl}}"
                  ],
                  "query": [],
                  "variable": [
                    {
                      "disabled": false,
                      "type": "any",
                      "value": "<uuid>",
                      "key": "id",
                      "description": "(Required) "
                    },
                    {
                      "description": {
                        "content": "",
                        "type": "text/plain"
                      },
                      "type": "any",
                      "value": "{{host}}",
                      "key": "host"
                    },
                    {
                      "description": {
                        "content": "",
                        "type": "text/plain"
                      },
                      "type": "any",
                      "value": "{{port}}",
                      "key": "port"
                    }
                  ]
                },
                "header": [
                  {
                    "description": {
                      "content": "Added as a part of security scheme: oauth2",
                      "type": "text/plain"
                    },
                    "key": "Authorization",
                    "value": "<token>"
                  },
                  {
                    "key": "Accept",
                    "value": "application/json"
                  }
                ],
                "method": "PUT",
                "body": {
                  "mode": "raw",
                  "raw": "{\n  \"name\": \"<string>\",\n  \"type\": \"<string>\",\n  \"description\": \"<string>\",\n  \"properties\": [\n    {\n      \"name\": \"<string>\",\n      \"value\": \"<string>\",\n      \"isSecret\": \"<boolean>\"\n    },\n    {\n      \"name\": \"<string>\",\n      \"value\": \"<string>\",\n      \"isSecret\": \"<boolean>\"\n    }\n  ]\n}",
                  "options": {
                    "raw": {
                      "language": "json"
                    }
                  }
                }
              },
              "status": "OK",
              "code": 200,
              "header": [
                {
                  "key": "Content-Type",
                  "value": "application/json"
                }
              ],
              "body": "{\n  \"id\": \"<uuid>\",\n  \"name\": \"<string>\",\n  \"type\": \"<string>\",\n  \"description\": \"<string>\",\n  \"properties\": [\n    {\n      \"name\": \"<string>\",\n      \"value\": \"<string>\",\n      \"isSecret\": \"<boolean>\"\n    },\n    {\n      \"name\": \"<string>\",\n      \"value\": \"<string>\",\n      \"isSecret\": \"<boolean>\"\n    }\n  ]\n}",
              "cookie": [],
              "_postman_previewlanguage": "json"
            },
            {
              "id": "01710d9c-49ec-4cb4-91b9-ad97a7ffbf08",
              "name": "Bad request",
              "originalRequest": {
                "url": {
                  "path": [
                    "identity-providers",
                    ":id"
                  ],
                  "host": [
                    "{{baseUrl}}"
                  ],
                  "query": [],
                  "variable": [
                    {
                      "disabled": false,
                      "type": "any",
                      "value": "<uuid>",
                      "key": "id",
                      "description": "(Required) "
                    },
                    {
                      "description": {
                        "content": "",
                        "type": "text/plain"
                      },
                      "type": "any",
                      "value": "{{host}}",
                      "key": "host"
                    },
                    {
                      "description": {
                        "content": "",
                        "type": "text/plain"
                      },
                      "type": "any",
                      "value": "{{port}}",
                      "key": "port"
                    }
                  ]
                },
                "header": [
                  {
                    "description": {
                      "content": "Added as a part of security scheme: oauth2",
                      "type": "text/plain"
                    },
                    "key": "Authorization",
                    "value": "<token>"
                  },
                  {
                    "key": "Accept",
                    "value": "application/json"
                  }
                ],
                "method": "PUT",
                "body": {
                  "mode": "raw",
                  "raw": "{\n  \"name\": \"<string>\",\n  \"type\": \"<string>\",\n  \"description\": \"<string>\",\n  \"properties\": [\n    {\n      \"name\": \"<string>\",\n      \"value\": \"<string>\",\n      \"isSecret\": \"<boolean>\"\n    },\n    {\n      \"name\": \"<string>\",\n      \"value\": \"<string>\",\n      \"isSecret\": \"<boolean>\"\n    }\n  ]\n}",
                  "options": {
                    "raw": {
                      "language": "json"
                    }
                  }
                }
              },
              "status": "Bad Request",
              "code": 400,
              "header": [
                {
                  "key": "Content-Type",
                  "value": "application/json"
                }
              ],
              "body": "{\n  \"code\": \"<string>\",\n  \"message\": {\n    \"key\": \"<string>\",\n    \"defaultValue\": \"<string>\"\n  },\n  \"description\": {\n    \"key\": \"<string>\",\n    \"defaultValue\": \"<string>\"\n  }\n}",
              "cookie": [],
              "_postman_previewlanguage": "json"
            },
            {
              "id": "e8f415d0-6a8e-4d40-845e-23908080586d",
              "name": "Identity provider not found",
              "originalRequest": {
                "url": {
                  "path": [
                    "identity-providers",
                    ":id"
                  ],
                  "host": [
                    "{{baseUrl}}"
                  ],
                  "query": [],
                  "variable": [
                    {
                      "disabled": false,
                      "type": "any",
                      "value": "<uuid>",
                      "key": "id",
                      "description": "(Required) "
                    },
                    {
                      "description": {
                        "content": "",
                        "type": "text/plain"
                      },
                      "type": "any",
                      "value": "{{host}}",
                      "key": "host"
                    },
                    {
                      "description": {
                        "content": "",
                        "type": "text/plain"
                      },
                      "type": "any",
                      "value": "{{port}}",
                      "key": "port"
                    }
                  ]
                },
                "header": [
                  {
                    "description": {
                      "content": "Added as a part of security scheme: oauth2",
                      "type": "text/plain"
                    },
                    "key": "Authorization",
                    "value": "<token>"
                  },
                  {
                    "key": "Accept",
                    "value": "application/json"
                  }
                ],
                "method": "PUT",
                "body": {
                  "mode": "raw",
                  "raw": "{\n  \"name\": \"<string>\",\n  \"type\": \"<string>\",\n  \"description\": \"<string>\",\n  \"properties\": [\n    {\n      \"name\": \"<string>\",\n      \"value\": \"<string>\",\n      \"isSecret\": \"<boolean>\"\n    },\n    {\n      \"name\": \"<string>\",\n      \"value\": \"<string>\",\n      \"isSecret\": \"<boolean>\"\n    }\n  ]\n}",
                  "options": {
                    "raw": {
                      "language": "json"
                    }
                  }
                }
              },
              "status": "Not Found",
              "code": 404,
              "header": [
                {
                  "key": "Content-Type",
                  "value": "application/json"
                }
              ],
              "body": "{\n  \"code\": \"<string>\",\n  \"message\": {\n    \"key\": \"<string>\",\n    \"defaultValue\": \"<string>\"\n  },\n  \"description\": {\n    \"key\": \"<string>\",\n    \"defaultValue\": \"<string>\"\n  }\n}",
              "cookie": [],
              "_postman_previewlanguage": "json"
            },
            {
              "id": "9c3cdf07-c215-478e-b23d-69b054ed6cff",
              "name": "Conflict",
              "originalRequest": {
                "url": {
                  "path": [
                    "identity-providers",
                    ":id"
                  ],
                  "host": [
                    "{{baseUrl}}"
                  ],
                  "query": [],
                  "variable": [
                    {
                      "disabled": false,
                      "type": "any",
                      "value": "<uuid>",
                      "key": "id",
                      "description": "(Required) "
                    },
                    {
                      "description": {
                        "content": "",
                        "type": "text/plain"
                      },
                      "type": "any",
                      "value": "{{host}}",
                      "key": "host"
                    },
                    {
                      "description": {
                        "content": "",
                        "type": "text/plain"
                      },
                      "type": "any",
                      "value": "{{port}}",
                      "key": "port"
                    }
                  ]
                },
                "header": [
                  {
                    "description": {
                      "content": "Added as a part of security scheme: oauth2",
                      "type": "text/plain"
                    },
                    "key": "Authorization",
                    "value": "<token>"
                  },
                  {
                    "key": "Accept",
                    "value": "application/json"
                  }
                ],
                "method": "PUT",
                "body": {
                  "mode": "raw",
                  "raw": "{\n  \"name\": \"<string>\",\n  \"type\": \"<string>\",\n  \"description\": \"<string>\",\n  \"properties\": [\n    {\n      \"name\": \"<string>\",\n      \"value\": \"<string>\",\n      \"isSecret\": \"<boolean>\"\n    },\n    {\n      \"name\": \"<string>\",\n      \"value\": \"<string>\",\n      \"isSecret\": \"<boolean>\"\n    }\n  ]\n}",
                  "options": {
                    "raw": {
                      "language": "json"
                    }
                  }
                }
              },
              "status": "Conflict",
              "code": 409,
              "header": [
                {
                  "key": "Content-Type",
                  "value": "application/json"
                }
              ],
              "body": "{\n  \"code\": \"<string>\",\n  \"message\": {\n    \"key\": \"<string>\",\n    \"defaultValue\": \"<string>\"\n  },\n  \"description\": {\n    \"key\": \"<string>\",\n    \"defaultValue\": \"<string>\"\n  }\n}",
              "cookie": [],
              "_postman_previewlanguage": "json"
            },
            {
              "id": "a024a52c-6524-4dd3-8fc7-06b12c800b6b",
              "name": "Internal server error",
              "originalRequest": {
                "url": {
                  "path": [
                    "identity-providers",
                    ":id"
                  ],
                  "host": [
                    "{{baseUrl}}"
                  ],
                  "query": [],
                  "variable": [
                    {
                      "disabled": false,
                      "type": "any",
                      "value": "<uuid>",
                      "key": "id",
                      "description": "(Required) "
                    },
                    {
                      "description": {
                        "content": "",
                        "type": "text/plain"
                      },
                      "type": "any",
                      "value": "{{host}}",
                      "key": "host"
                    },
                    {
                      "description": {
                        "content": "",
                        "type": "text/plain"
                      },
                      "type": "any",
                      "value": "{{port}}",
                      "key": "port"
                    }
                  ]
                },
                "header": [
                  {
                    "description": {
                      "content": "Added as a part of security scheme: oauth2",
                      "type": "text/plain"
                    },
                    "key": "Authorization",
                    "value": "<token>"
                  }
                ],
                "method": "PUT",
                "body": {
                  "mode": "raw",
                  "raw": "{\n  \"name\": \"<string>\",\n  \"type\": \"<string>\",\n  \"description\": \"<string>\",\n  \"properties\": [\n    {\n      \"name\": \"<string>\",\n      \"value\": \"<string>\",\n      \"isSecret\": \"<boolean>\"\n    },\n    {\n      \"name\": \"<string>\",\n      \"value\": \"<string>\",\n      \"isSecret\": \"<boolean>\"\n    }\n  ]\n}",
                  "options": {
                    "raw": {
                      "language": "json"
                    }
                  }
                }
              },
              "status": "Internal Server Error",
              "code": 500,
              "header": [
                {
                  "key": "Content-Type",
                  "value": "text/plain"
                }
              ],
              "body": "",
              "cookie": [],
              "_postman_previewlanguage": "text"
            }
          ],
          "event": [],
          "protocolProfileBehavior": {
            "disableBodyPruning": true
          }
        },
        {
          "id": "6bd9fcd4-eb6f-4464-be2a-47a59a8e4570",
          "name": "Delete an identity provider",
          "request": {
            "name": "Delete an identity provider",
            "description": {},
            "url": {
              "path": [
                "identity-providers",
                ":id"
              ],
              "host": [
                "{{baseUrl}}"
              ],
              "query": [],
              "variable": [
                {
                  "disabled": false,
                  "type": "any",
                  "value": "<uuid>",
                  "key": "id",
                  "description": "(Required) "
                },
                {
                  "description": {
                    "content": "",
                    "type": "text/plain"
                  },
                  "type": "any",
                  "value": "{{host}}",
                  "key": "host"
                },
                {
                  "description": {
                    "content": "",
                    "type": "text/plain"
                  },
                  "type": "any",
                  "value": "{{port}}",
                  "key": "port"
                }
              ]
            },
            "header": [
              {
                "key": "Accept",
                "value": "application/json"
              }
            ],
            "method": "DELETE",
            "auth": null
          },
          "response": [
            {
              "id": "e7e15c13-75b5-42a3-807e-bff3f20c891e",
              "name": "Identity provider deleted",
              "originalRequest": {
                "url": {
                  "path": [
                    "identity-providers",
                    ":id"
                  ],
                  "host": [
                    "{{baseUrl}}"
                  ],
                  "query": [],
                  "variable": [
                    {
                      "disabled": false,
                      "type": "any",
                      "value": "<uuid>",
                      "key": "id",
                      "description": "(Required) "
                    },
                    {
                      "description": {
                        "content": "",
                        "type": "text/plain"
                      },
                      "type": "any",
                      "value": "{{host}}",
                      "key": "host"
                    },
                    {
                      "description": {
                        "content": "",
                        "type": "text/plain"
                      },
                      "type": "any",
                      "value": "{{port}}",
                      "key": "port"
                    }
                  ]
                },
                "header": [
                  {
                    "description": {
                      "content": "Added as a part of security scheme: oauth2",
                      "type": "text/plain"
                    },
                    "key": "Authorization",
                    "value": "<token>"
                  }
                ],
                "method": "DELETE",
                "body": {}
              },
              "status": "No Content",
              "code": 204,
              "header": [
                {
                  "key": "Content-Type",
                  "value": "text/plain"
                }
              ],
              "body": "",
              "cookie": [],
              "_postman_previewlanguage": "text"
            },
            {
              "id": "afb8fc8a-36ac-4437-8273-3f8433574144",
              "name": "Bad request",
              "originalRequest": {
                "url": {
                  "path": [
                    "identity-providers",
                    ":id"
                  ],
                  "host": [
                    "{{baseUrl}}"
                  ],
                  "query": [],
                  "variable": [
                    {
                      "disabled": false,
                      "type": "any",
                      "value": "<uuid>",
                      "key": "id",
                      "description": "(Required) "
                    },
                    {
                      "description": {
                        "content": "",
                        "type": "text/plain"
                      },
                      "type": "any",
                      "value": "{{host}}",
                      "key": "host"
                    },
                    {
                      "description": {
                        "content": "",
                        "type": "text/plain"
                      },
                      "type": "any",
                      "value": "{{port}}",
                      "key": "port"
                    }
                  ]
                },
                "header": [
                  {
                    "description": {
                      "content": "Added as a part of security scheme: oauth2",
                      "type": "text/plain"
                    },
                    "key": "Authorization",
                    "value": "<token>"
                  },
                  {
                    "key": "Accept",
                    "value": "application/json"
                  }
                ],
                "method": "DELETE",
                "body": {}
              },
              "status": "Bad Request",
              "code": 400,
              "header": [
                {
                  "key": "Content-Type",
                  "value": "application/json"
                }
              ],
              "body": "{\n  \"code\": \"<string>\",\n  \"message\": {\n    \"key\": \"<string>\",\n    \"defaultValue\": \"<string>\"\n  },\n  \"description\": {\n    \"key\": \"<string>\",\n    \"defaultValue\": \"<string>\"\n  }\n}",
              "cookie": [],
              "_postman_previewlanguage": "json"
            },
            {
              "id": "36d4c2e9-4d1a-46d8-8e8c-c74ca1b32dea",
              "name": "Internal server error",
              "originalRequest": {
                "url": {
                  "path": [
                    "identity-providers",
                    ":id"
                  ],
                  "host": [
                    "{{baseUrl}}"
                  ],
                  "query": [],
                  "variable": [
                    {
                      "disabled": false,
                      "type": "any",
                      "value": "<uuid>",
                      "key": "id",
                      "description": "(Required) "
                    },
                    {
                      "description": {
                        "content": "",
                        "type": "text/plain"
                      },
                      "type": "any",
                      "value": "{{host}}",
                      "key": "host"
                    },
                    {
                      "description": {
                        "content": "",
                        "type": "text/plain"
                      },
                      "type": "any",
                      "value": "{{port}}",
                      "key": "port"
                    }
                  ]
                },
                "header": [
                  {
                    "description": {
                      "content": "Added as a part of security scheme: oauth2",
                      "type": "text/plain"
                    },
                    "key": "Authorization",
                    "value": "<token>"
                  }
                ],
                "method": "DELETE",
                "body": {}
              },
              "status": "Internal Server Error",
              "code": 500,
              "header": [
                {
                  "key": "Content-Type",
                  "value": "text/plain"
                }
              ],
              "body": "",
              "cookie": [],
              "_postman_previewlanguage": "text"
            }
          ],
          "event": [],
          "protocolProfileBehavior": {
            "disableBodyPruning": true
          }
        }
      ],
      "event": []
    }
  ],
  "event": [],
  "variable": [
    {
      "description": {
        "content": "",
        "type": "text/plain"
      },
      "type": "any",
      "value": "localhost",
      "key": "host"
    },
    {
      "description": {
        "content": "",
        "type": "text/plain"
      },
      "type": "any",
      "value": "8090",
      "key": "port"
    },
    {
      "type": "string",
      "value": "https://{{host}}:{{port}}",
      "key": "baseUrl"
    },
    {
      "key": "clientId",
      "value": "",
      "type": "string"
    },
    {
      "key": "clientSecret",
      "value": "",
      "type": "string"
    }
  ],
  "auth": {
    "type": "oauth2",
    "oauth2": [
      {
        "key": "grant_type",
        "value": "client_credentials"
      },
      {
        "key": "accessTokenUrl",
        "value": "{{baseUrl}}/oauth2/token"
      },
      {
        "key": "clientId",
        "value": "{{clientId}}"
      },
      {
        "key": "clientSecret",
        "value": "{{clientSecret}}"
      },
      {
        "key": "scope",
        "value": "system"
      },
      {
        "key": "addTokenTo",
        "value": "header"
      }
    ]
  },
  "info": {
    "_postman_id": "36ee809b-ebdb-452f-8bb4-8bb131ba1740",
    "name": "Identity Provider Management API",
    "schema": "https://schema.getpostman.com/json/collection/v2.1.0/collection.json",
    "description": {
      "content": "Configure external identity providers for federated login. Supports social providers such as Google and GitHub, as well as custom OIDC providers.",
      "type": "text/plain"
    }
  }
}