{
  "item": [
    {
      "id": "45db7cc1-23c4-44bc-ae78-bd03ad0b952d",
      "name": "Message Senders",
      "description": {
        "content": "Message notification sender management operations.",
        "type": "text/plain"
      },
      "item": [
        {
          "id": "c916c885-2c53-400e-b714-c09f2888d65f",
          "name": "List message notification senders",
          "request": {
            "name": "List message notification senders",
            "description": {
              "content": "Retrieve a list of message notification senders.",
              "type": "text/plain"
            },
            "url": {
              "path": [
                "notification-senders",
                "message"
              ],
              "host": [
                "{{baseUrl}}"
              ],
              "query": [],
              "variable": [
                {
                  "description": {
                    "content": "",
                    "type": "text/plain"
                  },
                  "type": "any",
                  "value": "{{host}}",
                  "key": "host"
                },
                {
                  "description": {
                    "content": "",
                    "type": "text/plain"
                  },
                  "type": "any",
                  "value": "{{port}}",
                  "key": "port"
                }
              ]
            },
            "header": [
              {
                "key": "Accept",
                "value": "application/json"
              }
            ],
            "method": "GET",
            "auth": null
          },
          "response": [
            {
              "id": "f03c8e0e-4b06-4c1a-b7a1-41dfcea19cae",
              "name": "OK",
              "originalRequest": {
                "url": {
                  "path": [
                    "notification-senders",
                    "message"
                  ],
                  "host": [
                    "{{baseUrl}}"
                  ],
                  "query": [],
                  "variable": [
                    {
                      "description": {
                        "content": "",
                        "type": "text/plain"
                      },
                      "type": "any",
                      "value": "{{host}}",
                      "key": "host"
                    },
                    {
                      "description": {
                        "content": "",
                        "type": "text/plain"
                      },
                      "type": "any",
                      "value": "{{port}}",
                      "key": "port"
                    }
                  ]
                },
                "header": [
                  {
                    "description": {
                      "content": "Added as a part of security scheme: oauth2",
                      "type": "text/plain"
                    },
                    "key": "Authorization",
                    "value": "<token>"
                  },
                  {
                    "key": "Accept",
                    "value": "application/json"
                  }
                ],
                "method": "GET",
                "body": {}
              },
              "status": "OK",
              "code": 200,
              "header": [
                {
                  "key": "Content-Type",
                  "value": "application/json"
                }
              ],
              "body": "[\n  {\n    \"id\": \"<string>\",\n    \"name\": \"<string>\",\n    \"description\": \"<string>\",\n    \"provider\": \"<string>\",\n    \"properties\": [\n      {\n        \"name\": \"<string>\",\n        \"value\": \"<string>\",\n        \"isSecret\": \"<boolean>\"\n      },\n      {\n        \"name\": \"<string>\",\n        \"value\": \"<string>\",\n        \"isSecret\": \"<boolean>\"\n      }\n    ]\n  },\n  {\n    \"id\": \"<string>\",\n    \"name\": \"<string>\",\n    \"description\": \"<string>\",\n    \"provider\": \"<string>\",\n    \"properties\": [\n      {\n        \"name\": \"<string>\",\n        \"value\": \"<string>\",\n        \"isSecret\": \"<boolean>\"\n      },\n      {\n        \"name\": \"<string>\",\n        \"value\": \"<string>\",\n        \"isSecret\": \"<boolean>\"\n      }\n    ]\n  }\n]",
              "cookie": [],
              "_postman_previewlanguage": "json"
            },
            {
              "id": "f043ada8-88cd-474a-a649-445b96cf47ae",
              "name": "Internal Server Error: An unexpected error occurred while processing the request",
              "originalRequest": {
                "url": {
                  "path": [
                    "notification-senders",
                    "message"
                  ],
                  "host": [
                    "{{baseUrl}}"
                  ],
                  "query": [],
                  "variable": [
                    {
                      "description": {
                        "content": "",
                        "type": "text/plain"
                      },
                      "type": "any",
                      "value": "{{host}}",
                      "key": "host"
                    },
                    {
                      "description": {
                        "content": "",
                        "type": "text/plain"
                      },
                      "type": "any",
                      "value": "{{port}}",
                      "key": "port"
                    }
                  ]
                },
                "header": [
                  {
                    "description": {
                      "content": "Added as a part of security scheme: oauth2",
                      "type": "text/plain"
                    },
                    "key": "Authorization",
                    "value": "<token>"
                  },
                  {
                    "key": "Accept",
                    "value": "application/json"
                  }
                ],
                "method": "GET",
                "body": {}
              },
              "status": "Internal Server Error",
              "code": 500,
              "header": [
                {
                  "key": "Content-Type",
                  "value": "application/json"
                }
              ],
              "body": "{\n  \"code\": \"<string>\",\n  \"message\": {\n    \"key\": \"<string>\",\n    \"defaultValue\": \"<string>\"\n  },\n  \"description\": {\n    \"key\": \"<string>\",\n    \"defaultValue\": \"<string>\"\n  }\n}",
              "cookie": [],
              "_postman_previewlanguage": "json"
            }
          ],
          "event": [],
          "protocolProfileBehavior": {
            "disableBodyPruning": true
          }
        },
        {
          "id": "b7bfc1d4-3c01-4ba7-8823-0243da35c81c",
          "name": "Create a new message notification sender",
          "request": {
            "name": "Create a new message notification sender",
            "description": {
              "content": "Create a new message notification sender with the provided details.",
              "type": "text/plain"
            },
            "url": {
              "path": [
                "notification-senders",
                "message"
              ],
              "host": [
                "{{baseUrl}}"
              ],
              "query": [],
              "variable": [
                {
                  "description": {
                    "content": "",
                    "type": "text/plain"
                  },
                  "type": "any",
                  "value": "{{host}}",
                  "key": "host"
                },
                {
                  "description": {
                    "content": "",
                    "type": "text/plain"
                  },
                  "type": "any",
                  "value": "{{port}}",
                  "key": "port"
                }
              ]
            },
            "header": [
              {
                "key": "Content-Type",
                "value": "application/json"
              },
              {
                "key": "Accept",
                "value": "application/json"
              }
            ],
            "method": "POST",
            "auth": null,
            "body": {
              "mode": "raw",
              "raw": "{\n  \"name\": \"<string>\",\n  \"provider\": \"<string>\",\n  \"description\": \"<string>\",\n  \"properties\": [\n    {\n      \"name\": \"<string>\",\n      \"value\": \"<string>\",\n      \"isSecret\": \"<boolean>\"\n    },\n    {\n      \"name\": \"<string>\",\n      \"value\": \"<string>\",\n      \"isSecret\": \"<boolean>\"\n    }\n  ]\n}",
              "options": {
                "raw": {
                  "language": "json"
                }
              }
            }
          },
          "response": [
            {
              "id": "a59f18e7-4e8b-4223-8131-9ad4ed34901b",
              "name": "Created",
              "originalRequest": {
                "url": {
                  "path": [
                    "notification-senders",
                    "message"
                  ],
                  "host": [
                    "{{baseUrl}}"
                  ],
                  "query": [],
                  "variable": [
                    {
                      "description": {
                        "content": "",
                        "type": "text/plain"
                      },
                      "type": "any",
                      "value": "{{host}}",
                      "key": "host"
                    },
                    {
                      "description": {
                        "content": "",
                        "type": "text/plain"
                      },
                      "type": "any",
                      "value": "{{port}}",
                      "key": "port"
                    }
                  ]
                },
                "header": [
                  {
                    "description": {
                      "content": "Added as a part of security scheme: oauth2",
                      "type": "text/plain"
                    },
                    "key": "Authorization",
                    "value": "<token>"
                  },
                  {
                    "key": "Accept",
                    "value": "application/json"
                  }
                ],
                "method": "POST",
                "body": {
                  "mode": "raw",
                  "raw": "{\n  \"name\": \"<string>\",\n  \"provider\": \"<string>\",\n  \"description\": \"<string>\",\n  \"properties\": [\n    {\n      \"name\": \"<string>\",\n      \"value\": \"<string>\",\n      \"isSecret\": \"<boolean>\"\n    },\n    {\n      \"name\": \"<string>\",\n      \"value\": \"<string>\",\n      \"isSecret\": \"<boolean>\"\n    }\n  ]\n}",
                  "options": {
                    "raw": {
                      "language": "json"
                    }
                  }
                }
              },
              "status": "Created",
              "code": 201,
              "header": [
                {
                  "key": "Content-Type",
                  "value": "application/json"
                }
              ],
              "body": "{\n  \"id\": \"<string>\",\n  \"name\": \"<string>\",\n  \"description\": \"<string>\",\n  \"provider\": \"<string>\",\n  \"properties\": [\n    {\n      \"name\": \"<string>\",\n      \"value\": \"<string>\",\n      \"isSecret\": \"<boolean>\"\n    },\n    {\n      \"name\": \"<string>\",\n      \"value\": \"<string>\",\n      \"isSecret\": \"<boolean>\"\n    }\n  ]\n}",
              "cookie": [],
              "_postman_previewlanguage": "json"
            },
            {
              "id": "1f65aa55-d29c-4341-bcfc-01d858689f3b",
              "name": "Bad Request: The request body is malformed or contains invalid data",
              "originalRequest": {
                "url": {
                  "path": [
                    "notification-senders",
                    "message"
                  ],
                  "host": [
                    "{{baseUrl}}"
                  ],
                  "query": [],
                  "variable": [
                    {
                      "description": {
                        "content": "",
                        "type": "text/plain"
                      },
                      "type": "any",
                      "value": "{{host}}",
                      "key": "host"
                    },
                    {
                      "description": {
                        "content": "",
                        "type": "text/plain"
                      },
                      "type": "any",
                      "value": "{{port}}",
                      "key": "port"
                    }
                  ]
                },
                "header": [
                  {
                    "description": {
                      "content": "Added as a part of security scheme: oauth2",
                      "type": "text/plain"
                    },
                    "key": "Authorization",
                    "value": "<token>"
                  },
                  {
                    "key": "Accept",
                    "value": "application/json"
                  }
                ],
                "method": "POST",
                "body": {
                  "mode": "raw",
                  "raw": "{\n  \"name\": \"<string>\",\n  \"provider\": \"<string>\",\n  \"description\": \"<string>\",\n  \"properties\": [\n    {\n      \"name\": \"<string>\",\n      \"value\": \"<string>\",\n      \"isSecret\": \"<boolean>\"\n    },\n    {\n      \"name\": \"<string>\",\n      \"value\": \"<string>\",\n      \"isSecret\": \"<boolean>\"\n    }\n  ]\n}",
                  "options": {
                    "raw": {
                      "language": "json"
                    }
                  }
                }
              },
              "status": "Bad Request",
              "code": 400,
              "header": [
                {
                  "key": "Content-Type",
                  "value": "application/json"
                }
              ],
              "body": "{\n  \"code\": \"<string>\",\n  \"message\": {\n    \"key\": \"<string>\",\n    \"defaultValue\": \"<string>\"\n  },\n  \"description\": {\n    \"key\": \"<string>\",\n    \"defaultValue\": \"<string>\"\n  }\n}",
              "cookie": [],
              "_postman_previewlanguage": "json"
            },
            {
              "id": "28b2d386-d29c-431c-86ee-dd5a9f8e913d",
              "name": "Conflict: A message notification sender with the same name already exists",
              "originalRequest": {
                "url": {
                  "path": [
                    "notification-senders",
                    "message"
                  ],
                  "host": [
                    "{{baseUrl}}"
                  ],
                  "query": [],
                  "variable": [
                    {
                      "description": {
                        "content": "",
                        "type": "text/plain"
                      },
                      "type": "any",
                      "value": "{{host}}",
                      "key": "host"
                    },
                    {
                      "description": {
                        "content": "",
                        "type": "text/plain"
                      },
                      "type": "any",
                      "value": "{{port}}",
                      "key": "port"
                    }
                  ]
                },
                "header": [
                  {
                    "description": {
                      "content": "Added as a part of security scheme: oauth2",
                      "type": "text/plain"
                    },
                    "key": "Authorization",
                    "value": "<token>"
                  },
                  {
                    "key": "Accept",
                    "value": "application/json"
                  }
                ],
                "method": "POST",
                "body": {
                  "mode": "raw",
                  "raw": "{\n  \"name\": \"<string>\",\n  \"provider\": \"<string>\",\n  \"description\": \"<string>\",\n  \"properties\": [\n    {\n      \"name\": \"<string>\",\n      \"value\": \"<string>\",\n      \"isSecret\": \"<boolean>\"\n    },\n    {\n      \"name\": \"<string>\",\n      \"value\": \"<string>\",\n      \"isSecret\": \"<boolean>\"\n    }\n  ]\n}",
                  "options": {
                    "raw": {
                      "language": "json"
                    }
                  }
                }
              },
              "status": "Conflict",
              "code": 409,
              "header": [
                {
                  "key": "Content-Type",
                  "value": "application/json"
                }
              ],
              "body": "{\n  \"code\": \"<string>\",\n  \"message\": {\n    \"key\": \"<string>\",\n    \"defaultValue\": \"<string>\"\n  },\n  \"description\": {\n    \"key\": \"<string>\",\n    \"defaultValue\": \"<string>\"\n  }\n}",
              "cookie": [],
              "_postman_previewlanguage": "json"
            },
            {
              "id": "4f4fe4a4-589a-4a8f-a5ce-667669818adb",
              "name": "Internal Server Error: An unexpected error occurred while processing the request",
              "originalRequest": {
                "url": {
                  "path": [
                    "notification-senders",
                    "message"
                  ],
                  "host": [
                    "{{baseUrl}}"
                  ],
                  "query": [],
                  "variable": [
                    {
                      "description": {
                        "content": "",
                        "type": "text/plain"
                      },
                      "type": "any",
                      "value": "{{host}}",
                      "key": "host"
                    },
                    {
                      "description": {
                        "content": "",
                        "type": "text/plain"
                      },
                      "type": "any",
                      "value": "{{port}}",
                      "key": "port"
                    }
                  ]
                },
                "header": [
                  {
                    "description": {
                      "content": "Added as a part of security scheme: oauth2",
                      "type": "text/plain"
                    },
                    "key": "Authorization",
                    "value": "<token>"
                  },
                  {
                    "key": "Accept",
                    "value": "application/json"
                  }
                ],
                "method": "POST",
                "body": {
                  "mode": "raw",
                  "raw": "{\n  \"name\": \"<string>\",\n  \"provider\": \"<string>\",\n  \"description\": \"<string>\",\n  \"properties\": [\n    {\n      \"name\": \"<string>\",\n      \"value\": \"<string>\",\n      \"isSecret\": \"<boolean>\"\n    },\n    {\n      \"name\": \"<string>\",\n      \"value\": \"<string>\",\n      \"isSecret\": \"<boolean>\"\n    }\n  ]\n}",
                  "options": {
                    "raw": {
                      "language": "json"
                    }
                  }
                }
              },
              "status": "Internal Server Error",
              "code": 500,
              "header": [
                {
                  "key": "Content-Type",
                  "value": "application/json"
                }
              ],
              "body": "{\n  \"code\": \"<string>\",\n  \"message\": {\n    \"key\": \"<string>\",\n    \"defaultValue\": \"<string>\"\n  },\n  \"description\": {\n    \"key\": \"<string>\",\n    \"defaultValue\": \"<string>\"\n  }\n}",
              "cookie": [],
              "_postman_previewlanguage": "json"
            }
          ],
          "event": [],
          "protocolProfileBehavior": {
            "disableBodyPruning": true
          }
        },
        {
          "id": "1ee7449f-0d05-4d88-9226-0d882fdc95c1",
          "name": "Get a message notification sender by ID",
          "request": {
            "name": "Get a message notification sender by ID",
            "description": {
              "content": "Retrieve a message notification sender by its unique identifier.",
              "type": "text/plain"
            },
            "url": {
              "path": [
                "notification-senders",
                "message",
                ":id"
              ],
              "host": [
                "{{baseUrl}}"
              ],
              "query": [],
              "variable": [
                {
                  "disabled": false,
                  "type": "any",
                  "value": "<string>",
                  "key": "id",
                  "description": "(Required) Unique identifier of the message notification sender"
                },
                {
                  "description": {
                    "content": "",
                    "type": "text/plain"
                  },
                  "type": "any",
                  "value": "{{host}}",
                  "key": "host"
                },
                {
                  "description": {
                    "content": "",
                    "type": "text/plain"
                  },
                  "type": "any",
                  "value": "{{port}}",
                  "key": "port"
                }
              ]
            },
            "header": [
              {
                "key": "Accept",
                "value": "application/json"
              }
            ],
            "method": "GET",
            "auth": null
          },
          "response": [
            {
              "id": "aa349db5-8d28-4ed7-afac-d218448a2bb9",
              "name": "OK",
              "originalRequest": {
                "url": {
                  "path": [
                    "notification-senders",
                    "message",
                    ":id"
                  ],
                  "host": [
                    "{{baseUrl}}"
                  ],
                  "query": [],
                  "variable": [
                    {
                      "disabled": false,
                      "type": "any",
                      "value": "<string>",
                      "key": "id",
                      "description": "(Required) Unique identifier of the message notification sender"
                    },
                    {
                      "description": {
                        "content": "",
                        "type": "text/plain"
                      },
                      "type": "any",
                      "value": "{{host}}",
                      "key": "host"
                    },
                    {
                      "description": {
                        "content": "",
                        "type": "text/plain"
                      },
                      "type": "any",
                      "value": "{{port}}",
                      "key": "port"
                    }
                  ]
                },
                "header": [
                  {
                    "description": {
                      "content": "Added as a part of security scheme: oauth2",
                      "type": "text/plain"
                    },
                    "key": "Authorization",
                    "value": "<token>"
                  },
                  {
                    "key": "Accept",
                    "value": "application/json"
                  }
                ],
                "method": "GET",
                "body": {}
              },
              "status": "OK",
              "code": 200,
              "header": [
                {
                  "key": "Content-Type",
                  "value": "application/json"
                }
              ],
              "body": "{\n  \"id\": \"<string>\",\n  \"name\": \"<string>\",\n  \"description\": \"<string>\",\n  \"provider\": \"<string>\",\n  \"properties\": [\n    {\n      \"name\": \"<string>\",\n      \"value\": \"<string>\",\n      \"isSecret\": \"<boolean>\"\n    },\n    {\n      \"name\": \"<string>\",\n      \"value\": \"<string>\",\n      \"isSecret\": \"<boolean>\"\n    }\n  ]\n}",
              "cookie": [],
              "_postman_previewlanguage": "json"
            },
            {
              "id": "0d034335-a766-47bb-84b1-ee02a7d6fc84",
              "name": "Bad Request: Invalid sender ID provided",
              "originalRequest": {
                "url": {
                  "path": [
                    "notification-senders",
                    "message",
                    ":id"
                  ],
                  "host": [
                    "{{baseUrl}}"
                  ],
                  "query": [],
                  "variable": [
                    {
                      "disabled": false,
                      "type": "any",
                      "value": "<string>",
                      "key": "id",
                      "description": "(Required) Unique identifier of the message notification sender"
                    },
                    {
                      "description": {
                        "content": "",
                        "type": "text/plain"
                      },
                      "type": "any",
                      "value": "{{host}}",
                      "key": "host"
                    },
                    {
                      "description": {
                        "content": "",
                        "type": "text/plain"
                      },
                      "type": "any",
                      "value": "{{port}}",
                      "key": "port"
                    }
                  ]
                },
                "header": [
                  {
                    "description": {
                      "content": "Added as a part of security scheme: oauth2",
                      "type": "text/plain"
                    },
                    "key": "Authorization",
                    "value": "<token>"
                  },
                  {
                    "key": "Accept",
                    "value": "application/json"
                  }
                ],
                "method": "GET",
                "body": {}
              },
              "status": "Bad Request",
              "code": 400,
              "header": [
                {
                  "key": "Content-Type",
                  "value": "application/json"
                }
              ],
              "body": "{\n  \"code\": \"<string>\",\n  \"message\": {\n    \"key\": \"<string>\",\n    \"defaultValue\": \"<string>\"\n  },\n  \"description\": {\n    \"key\": \"<string>\",\n    \"defaultValue\": \"<string>\"\n  }\n}",
              "cookie": [],
              "_postman_previewlanguage": "json"
            },
            {
              "id": "aaf2e443-58c8-4ee3-a438-0943efe50991",
              "name": "Not Found: The specified message notification sender does not exist",
              "originalRequest": {
                "url": {
                  "path": [
                    "notification-senders",
                    "message",
                    ":id"
                  ],
                  "host": [
                    "{{baseUrl}}"
                  ],
                  "query": [],
                  "variable": [
                    {
                      "disabled": false,
                      "type": "any",
                      "value": "<string>",
                      "key": "id",
                      "description": "(Required) Unique identifier of the message notification sender"
                    },
                    {
                      "description": {
                        "content": "",
                        "type": "text/plain"
                      },
                      "type": "any",
                      "value": "{{host}}",
                      "key": "host"
                    },
                    {
                      "description": {
                        "content": "",
                        "type": "text/plain"
                      },
                      "type": "any",
                      "value": "{{port}}",
                      "key": "port"
                    }
                  ]
                },
                "header": [
                  {
                    "description": {
                      "content": "Added as a part of security scheme: oauth2",
                      "type": "text/plain"
                    },
                    "key": "Authorization",
                    "value": "<token>"
                  },
                  {
                    "key": "Accept",
                    "value": "application/json"
                  }
                ],
                "method": "GET",
                "body": {}
              },
              "status": "Not Found",
              "code": 404,
              "header": [
                {
                  "key": "Content-Type",
                  "value": "application/json"
                }
              ],
              "body": "{\n  \"code\": \"<string>\",\n  \"message\": {\n    \"key\": \"<string>\",\n    \"defaultValue\": \"<string>\"\n  },\n  \"description\": {\n    \"key\": \"<string>\",\n    \"defaultValue\": \"<string>\"\n  }\n}",
              "cookie": [],
              "_postman_previewlanguage": "json"
            },
            {
              "id": "63ae5dfd-632e-4941-8ffe-669a6e3ee7e3",
              "name": "Internal Server Error: An unexpected error occurred while processing the request",
              "originalRequest": {
                "url": {
                  "path": [
                    "notification-senders",
                    "message",
                    ":id"
                  ],
                  "host": [
                    "{{baseUrl}}"
                  ],
                  "query": [],
                  "variable": [
                    {
                      "disabled": false,
                      "type": "any",
                      "value": "<string>",
                      "key": "id",
                      "description": "(Required) Unique identifier of the message notification sender"
                    },
                    {
                      "description": {
                        "content": "",
                        "type": "text/plain"
                      },
                      "type": "any",
                      "value": "{{host}}",
                      "key": "host"
                    },
                    {
                      "description": {
                        "content": "",
                        "type": "text/plain"
                      },
                      "type": "any",
                      "value": "{{port}}",
                      "key": "port"
                    }
                  ]
                },
                "header": [
                  {
                    "description": {
                      "content": "Added as a part of security scheme: oauth2",
                      "type": "text/plain"
                    },
                    "key": "Authorization",
                    "value": "<token>"
                  },
                  {
                    "key": "Accept",
                    "value": "application/json"
                  }
                ],
                "method": "GET",
                "body": {}
              },
              "status": "Internal Server Error",
              "code": 500,
              "header": [
                {
                  "key": "Content-Type",
                  "value": "application/json"
                }
              ],
              "body": "{\n  \"code\": \"<string>\",\n  \"message\": {\n    \"key\": \"<string>\",\n    \"defaultValue\": \"<string>\"\n  },\n  \"description\": {\n    \"key\": \"<string>\",\n    \"defaultValue\": \"<string>\"\n  }\n}",
              "cookie": [],
              "_postman_previewlanguage": "json"
            }
          ],
          "event": [],
          "protocolProfileBehavior": {
            "disableBodyPruning": true
          }
        },
        {
          "id": "a3cceb52-a086-42c1-99a8-c54a7e833845",
          "name": "Update a message notification sender",
          "request": {
            "name": "Update a message notification sender",
            "description": {
              "content": "Update an existing message notification sender with the provided details.",
              "type": "text/plain"
            },
            "url": {
              "path": [
                "notification-senders",
                "message",
                ":id"
              ],
              "host": [
                "{{baseUrl}}"
              ],
              "query": [],
              "variable": [
                {
                  "disabled": false,
                  "type": "any",
                  "value": "<string>",
                  "key": "id",
                  "description": "(Required) Unique identifier of the message notification sender to update"
                },
                {
                  "description": {
                    "content": "",
                    "type": "text/plain"
                  },
                  "type": "any",
                  "value": "{{host}}",
                  "key": "host"
                },
                {
                  "description": {
                    "content": "",
                    "type": "text/plain"
                  },
                  "type": "any",
                  "value": "{{port}}",
                  "key": "port"
                }
              ]
            },
            "header": [
              {
                "key": "Content-Type",
                "value": "application/json"
              },
              {
                "key": "Accept",
                "value": "application/json"
              }
            ],
            "method": "PUT",
            "auth": null,
            "body": {
              "mode": "raw",
              "raw": "{\n  \"name\": \"<string>\",\n  \"provider\": \"<string>\",\n  \"description\": \"<string>\",\n  \"properties\": [\n    {\n      \"name\": \"<string>\",\n      \"value\": \"<string>\",\n      \"isSecret\": \"<boolean>\"\n    },\n    {\n      \"name\": \"<string>\",\n      \"value\": \"<string>\",\n      \"isSecret\": \"<boolean>\"\n    }\n  ]\n}",
              "options": {
                "raw": {
                  "language": "json"
                }
              }
            }
          },
          "response": [
            {
              "id": "716dc46c-83d2-4ca7-88ab-d95e93d2fd44",
              "name": "Updated successfully",
              "originalRequest": {
                "url": {
                  "path": [
                    "notification-senders",
                    "message",
                    ":id"
                  ],
                  "host": [
                    "{{baseUrl}}"
                  ],
                  "query": [],
                  "variable": [
                    {
                      "disabled": false,
                      "type": "any",
                      "value": "<string>",
                      "key": "id",
                      "description": "(Required) Unique identifier of the message notification sender to update"
                    },
                    {
                      "description": {
                        "content": "",
                        "type": "text/plain"
                      },
                      "type": "any",
                      "value": "{{host}}",
                      "key": "host"
                    },
                    {
                      "description": {
                        "content": "",
                        "type": "text/plain"
                      },
                      "type": "any",
                      "value": "{{port}}",
                      "key": "port"
                    }
                  ]
                },
                "header": [
                  {
                    "description": {
                      "content": "Added as a part of security scheme: oauth2",
                      "type": "text/plain"
                    },
                    "key": "Authorization",
                    "value": "<token>"
                  },
                  {
                    "key": "Accept",
                    "value": "application/json"
                  }
                ],
                "method": "PUT",
                "body": {
                  "mode": "raw",
                  "raw": "{\n  \"name\": \"<string>\",\n  \"provider\": \"<string>\",\n  \"description\": \"<string>\",\n  \"properties\": [\n    {\n      \"name\": \"<string>\",\n      \"value\": \"<string>\",\n      \"isSecret\": \"<boolean>\"\n    },\n    {\n      \"name\": \"<string>\",\n      \"value\": \"<string>\",\n      \"isSecret\": \"<boolean>\"\n    }\n  ]\n}",
                  "options": {
                    "raw": {
                      "language": "json"
                    }
                  }
                }
              },
              "status": "OK",
              "code": 200,
              "header": [
                {
                  "key": "Content-Type",
                  "value": "application/json"
                }
              ],
              "body": "{\n  \"id\": \"<string>\",\n  \"name\": \"<string>\",\n  \"description\": \"<string>\",\n  \"provider\": \"<string>\",\n  \"properties\": [\n    {\n      \"name\": \"<string>\",\n      \"value\": \"<string>\",\n      \"isSecret\": \"<boolean>\"\n    },\n    {\n      \"name\": \"<string>\",\n      \"value\": \"<string>\",\n      \"isSecret\": \"<boolean>\"\n    }\n  ]\n}",
              "cookie": [],
              "_postman_previewlanguage": "json"
            },
            {
              "id": "5664a9e1-e339-450e-b9f7-8ed6197ca2c5",
              "name": "Bad Request: Invalid sender ID or request body",
              "originalRequest": {
                "url": {
                  "path": [
                    "notification-senders",
                    "message",
                    ":id"
                  ],
                  "host": [
                    "{{baseUrl}}"
                  ],
                  "query": [],
                  "variable": [
                    {
                      "disabled": false,
                      "type": "any",
                      "value": "<string>",
                      "key": "id",
                      "description": "(Required) Unique identifier of the message notification sender to update"
                    },
                    {
                      "description": {
                        "content": "",
                        "type": "text/plain"
                      },
                      "type": "any",
                      "value": "{{host}}",
                      "key": "host"
                    },
                    {
                      "description": {
                        "content": "",
                        "type": "text/plain"
                      },
                      "type": "any",
                      "value": "{{port}}",
                      "key": "port"
                    }
                  ]
                },
                "header": [
                  {
                    "description": {
                      "content": "Added as a part of security scheme: oauth2",
                      "type": "text/plain"
                    },
                    "key": "Authorization",
                    "value": "<token>"
                  },
                  {
                    "key": "Accept",
                    "value": "application/json"
                  }
                ],
                "method": "PUT",
                "body": {
                  "mode": "raw",
                  "raw": "{\n  \"name\": \"<string>\",\n  \"provider\": \"<string>\",\n  \"description\": \"<string>\",\n  \"properties\": [\n    {\n      \"name\": \"<string>\",\n      \"value\": \"<string>\",\n      \"isSecret\": \"<boolean>\"\n    },\n    {\n      \"name\": \"<string>\",\n      \"value\": \"<string>\",\n      \"isSecret\": \"<boolean>\"\n    }\n  ]\n}",
                  "options": {
                    "raw": {
                      "language": "json"
                    }
                  }
                }
              },
              "status": "Bad Request",
              "code": 400,
              "header": [
                {
                  "key": "Content-Type",
                  "value": "application/json"
                }
              ],
              "body": "{\n  \"code\": \"<string>\",\n  \"message\": {\n    \"key\": \"<string>\",\n    \"defaultValue\": \"<string>\"\n  },\n  \"description\": {\n    \"key\": \"<string>\",\n    \"defaultValue\": \"<string>\"\n  }\n}",
              "cookie": [],
              "_postman_previewlanguage": "json"
            },
            {
              "id": "50cefccd-00ea-4a4c-8446-f4a49f10ddc7",
              "name": "Not Found: The specified message notification sender does not exist",
              "originalRequest": {
                "url": {
                  "path": [
                    "notification-senders",
                    "message",
                    ":id"
                  ],
                  "host": [
                    "{{baseUrl}}"
                  ],
                  "query": [],
                  "variable": [
                    {
                      "disabled": false,
                      "type": "any",
                      "value": "<string>",
                      "key": "id",
                      "description": "(Required) Unique identifier of the message notification sender to update"
                    },
                    {
                      "description": {
                        "content": "",
                        "type": "text/plain"
                      },
                      "type": "any",
                      "value": "{{host}}",
                      "key": "host"
                    },
                    {
                      "description": {
                        "content": "",
                        "type": "text/plain"
                      },
                      "type": "any",
                      "value": "{{port}}",
                      "key": "port"
                    }
                  ]
                },
                "header": [
                  {
                    "description": {
                      "content": "Added as a part of security scheme: oauth2",
                      "type": "text/plain"
                    },
                    "key": "Authorization",
                    "value": "<token>"
                  },
                  {
                    "key": "Accept",
                    "value": "application/json"
                  }
                ],
                "method": "PUT",
                "body": {
                  "mode": "raw",
                  "raw": "{\n  \"name\": \"<string>\",\n  \"provider\": \"<string>\",\n  \"description\": \"<string>\",\n  \"properties\": [\n    {\n      \"name\": \"<string>\",\n      \"value\": \"<string>\",\n      \"isSecret\": \"<boolean>\"\n    },\n    {\n      \"name\": \"<string>\",\n      \"value\": \"<string>\",\n      \"isSecret\": \"<boolean>\"\n    }\n  ]\n}",
                  "options": {
                    "raw": {
                      "language": "json"
                    }
                  }
                }
              },
              "status": "Not Found",
              "code": 404,
              "header": [
                {
                  "key": "Content-Type",
                  "value": "application/json"
                }
              ],
              "body": "{\n  \"code\": \"<string>\",\n  \"message\": {\n    \"key\": \"<string>\",\n    \"defaultValue\": \"<string>\"\n  },\n  \"description\": {\n    \"key\": \"<string>\",\n    \"defaultValue\": \"<string>\"\n  }\n}",
              "cookie": [],
              "_postman_previewlanguage": "json"
            },
            {
              "id": "f6fbef31-03cb-41b4-ab4f-8185ef2b6eaf",
              "name": "Internal Server Error: An unexpected error occurred while processing the request",
              "originalRequest": {
                "url": {
                  "path": [
                    "notification-senders",
                    "message",
                    ":id"
                  ],
                  "host": [
                    "{{baseUrl}}"
                  ],
                  "query": [],
                  "variable": [
                    {
                      "disabled": false,
                      "type": "any",
                      "value": "<string>",
                      "key": "id",
                      "description": "(Required) Unique identifier of the message notification sender to update"
                    },
                    {
                      "description": {
                        "content": "",
                        "type": "text/plain"
                      },
                      "type": "any",
                      "value": "{{host}}",
                      "key": "host"
                    },
                    {
                      "description": {
                        "content": "",
                        "type": "text/plain"
                      },
                      "type": "any",
                      "value": "{{port}}",
                      "key": "port"
                    }
                  ]
                },
                "header": [
                  {
                    "description": {
                      "content": "Added as a part of security scheme: oauth2",
                      "type": "text/plain"
                    },
                    "key": "Authorization",
                    "value": "<token>"
                  },
                  {
                    "key": "Accept",
                    "value": "application/json"
                  }
                ],
                "method": "PUT",
                "body": {
                  "mode": "raw",
                  "raw": "{\n  \"name\": \"<string>\",\n  \"provider\": \"<string>\",\n  \"description\": \"<string>\",\n  \"properties\": [\n    {\n      \"name\": \"<string>\",\n      \"value\": \"<string>\",\n      \"isSecret\": \"<boolean>\"\n    },\n    {\n      \"name\": \"<string>\",\n      \"value\": \"<string>\",\n      \"isSecret\": \"<boolean>\"\n    }\n  ]\n}",
                  "options": {
                    "raw": {
                      "language": "json"
                    }
                  }
                }
              },
              "status": "Internal Server Error",
              "code": 500,
              "header": [
                {
                  "key": "Content-Type",
                  "value": "application/json"
                }
              ],
              "body": "{\n  \"code\": \"<string>\",\n  \"message\": {\n    \"key\": \"<string>\",\n    \"defaultValue\": \"<string>\"\n  },\n  \"description\": {\n    \"key\": \"<string>\",\n    \"defaultValue\": \"<string>\"\n  }\n}",
              "cookie": [],
              "_postman_previewlanguage": "json"
            }
          ],
          "event": [],
          "protocolProfileBehavior": {
            "disableBodyPruning": true
          }
        },
        {
          "id": "a3c035a6-4639-40f5-9467-bf8d510e00e7",
          "name": "Delete a message notification sender",
          "request": {
            "name": "Delete a message notification sender",
            "description": {
              "content": "Delete a message notification sender using its unique identifier.",
              "type": "text/plain"
            },
            "url": {
              "path": [
                "notification-senders",
                "message",
                ":id"
              ],
              "host": [
                "{{baseUrl}}"
              ],
              "query": [],
              "variable": [
                {
                  "disabled": false,
                  "type": "any",
                  "value": "<string>",
                  "key": "id",
                  "description": "(Required) Unique identifier of the message notification sender to delete"
                },
                {
                  "description": {
                    "content": "",
                    "type": "text/plain"
                  },
                  "type": "any",
                  "value": "{{host}}",
                  "key": "host"
                },
                {
                  "description": {
                    "content": "",
                    "type": "text/plain"
                  },
                  "type": "any",
                  "value": "{{port}}",
                  "key": "port"
                }
              ]
            },
            "header": [
              {
                "key": "Accept",
                "value": "application/json"
              }
            ],
            "method": "DELETE",
            "auth": null
          },
          "response": [
            {
              "id": "9a749545-228e-4f7c-a458-f0ce6bf4c781",
              "name": "No Content - Successfully deleted the message notification sender",
              "originalRequest": {
                "url": {
                  "path": [
                    "notification-senders",
                    "message",
                    ":id"
                  ],
                  "host": [
                    "{{baseUrl}}"
                  ],
                  "query": [],
                  "variable": [
                    {
                      "disabled": false,
                      "type": "any",
                      "value": "<string>",
                      "key": "id",
                      "description": "(Required) Unique identifier of the message notification sender to delete"
                    },
                    {
                      "description": {
                        "content": "",
                        "type": "text/plain"
                      },
                      "type": "any",
                      "value": "{{host}}",
                      "key": "host"
                    },
                    {
                      "description": {
                        "content": "",
                        "type": "text/plain"
                      },
                      "type": "any",
                      "value": "{{port}}",
                      "key": "port"
                    }
                  ]
                },
                "header": [
                  {
                    "description": {
                      "content": "Added as a part of security scheme: oauth2",
                      "type": "text/plain"
                    },
                    "key": "Authorization",
                    "value": "<token>"
                  }
                ],
                "method": "DELETE",
                "body": {}
              },
              "status": "No Content",
              "code": 204,
              "header": [
                {
                  "key": "Content-Type",
                  "value": "text/plain"
                }
              ],
              "body": "",
              "cookie": [],
              "_postman_previewlanguage": "text"
            },
            {
              "id": "957ab332-9da6-4160-b4a1-35e888e82d24",
              "name": "Bad Request: Invalid sender ID provided",
              "originalRequest": {
                "url": {
                  "path": [
                    "notification-senders",
                    "message",
                    ":id"
                  ],
                  "host": [
                    "{{baseUrl}}"
                  ],
                  "query": [],
                  "variable": [
                    {
                      "disabled": false,
                      "type": "any",
                      "value": "<string>",
                      "key": "id",
                      "description": "(Required) Unique identifier of the message notification sender to delete"
                    },
                    {
                      "description": {
                        "content": "",
                        "type": "text/plain"
                      },
                      "type": "any",
                      "value": "{{host}}",
                      "key": "host"
                    },
                    {
                      "description": {
                        "content": "",
                        "type": "text/plain"
                      },
                      "type": "any",
                      "value": "{{port}}",
                      "key": "port"
                    }
                  ]
                },
                "header": [
                  {
                    "description": {
                      "content": "Added as a part of security scheme: oauth2",
                      "type": "text/plain"
                    },
                    "key": "Authorization",
                    "value": "<token>"
                  },
                  {
                    "key": "Accept",
                    "value": "application/json"
                  }
                ],
                "method": "DELETE",
                "body": {}
              },
              "status": "Bad Request",
              "code": 400,
              "header": [
                {
                  "key": "Content-Type",
                  "value": "application/json"
                }
              ],
              "body": "{\n  \"code\": \"<string>\",\n  \"message\": {\n    \"key\": \"<string>\",\n    \"defaultValue\": \"<string>\"\n  },\n  \"description\": {\n    \"key\": \"<string>\",\n    \"defaultValue\": \"<string>\"\n  }\n}",
              "cookie": [],
              "_postman_previewlanguage": "json"
            },
            {
              "id": "517830eb-c31c-43dd-a55d-28addf8f0a58",
              "name": "Internal Server Error: An unexpected error occurred while processing the request",
              "originalRequest": {
                "url": {
                  "path": [
                    "notification-senders",
                    "message",
                    ":id"
                  ],
                  "host": [
                    "{{baseUrl}}"
                  ],
                  "query": [],
                  "variable": [
                    {
                      "disabled": false,
                      "type": "any",
                      "value": "<string>",
                      "key": "id",
                      "description": "(Required) Unique identifier of the message notification sender to delete"
                    },
                    {
                      "description": {
                        "content": "",
                        "type": "text/plain"
                      },
                      "type": "any",
                      "value": "{{host}}",
                      "key": "host"
                    },
                    {
                      "description": {
                        "content": "",
                        "type": "text/plain"
                      },
                      "type": "any",
                      "value": "{{port}}",
                      "key": "port"
                    }
                  ]
                },
                "header": [
                  {
                    "description": {
                      "content": "Added as a part of security scheme: oauth2",
                      "type": "text/plain"
                    },
                    "key": "Authorization",
                    "value": "<token>"
                  },
                  {
                    "key": "Accept",
                    "value": "application/json"
                  }
                ],
                "method": "DELETE",
                "body": {}
              },
              "status": "Internal Server Error",
              "code": 500,
              "header": [
                {
                  "key": "Content-Type",
                  "value": "application/json"
                }
              ],
              "body": "{\n  \"code\": \"<string>\",\n  \"message\": {\n    \"key\": \"<string>\",\n    \"defaultValue\": \"<string>\"\n  },\n  \"description\": {\n    \"key\": \"<string>\",\n    \"defaultValue\": \"<string>\"\n  }\n}",
              "cookie": [],
              "_postman_previewlanguage": "json"
            }
          ],
          "event": [],
          "protocolProfileBehavior": {
            "disableBodyPruning": true
          }
        }
      ],
      "event": []
    },
    {
      "id": "1094d3ac-5824-4099-aa5b-3a69b68a6cc6",
      "name": "One Time Password (OTP)",
      "description": {
        "content": "OTP sender and OTP dispatch operations.",
        "type": "text/plain"
      },
      "item": [
        {
          "id": "c30d3afb-4078-4d54-b671-9715245992dd",
          "name": "Send a One Time Password (OTP)",
          "request": {
            "name": "Send a One Time Password (OTP)",
            "description": {
              "content": "Send a One Time Password (OTP) to a recipient using a specified message notification sender.",
              "type": "text/plain"
            },
            "url": {
              "path": [
                "notification-senders",
                "otp",
                "send"
              ],
              "host": [
                "{{baseUrl}}"
              ],
              "query": [],
              "variable": [
                {
                  "description": {
                    "content": "",
                    "type": "text/plain"
                  },
                  "type": "any",
                  "value": "{{host}}",
                  "key": "host"
                },
                {
                  "description": {
                    "content": "",
                    "type": "text/plain"
                  },
                  "type": "any",
                  "value": "{{port}}",
                  "key": "port"
                }
              ]
            },
            "header": [
              {
                "key": "Content-Type",
                "value": "application/json"
              },
              {
                "key": "Accept",
                "value": "application/json"
              }
            ],
            "method": "POST",
            "auth": null,
            "body": {
              "mode": "raw",
              "raw": "{\n  \"recipient\": \"<string>\",\n  \"senderId\": \"<string>\",\n  \"channel\": \"<string>\"\n}",
              "options": {
                "raw": {
                  "language": "json"
                }
              }
            }
          },
          "response": [
            {
              "id": "776ecf37-44ca-4cd4-8d03-35cecb2059fd",
              "name": "OTP sent successfully",
              "originalRequest": {
                "url": {
                  "path": [
                    "notification-senders",
                    "otp",
                    "send"
                  ],
                  "host": [
                    "{{baseUrl}}"
                  ],
                  "query": [],
                  "variable": [
                    {
                      "description": {
                        "content": "",
                        "type": "text/plain"
                      },
                      "type": "any",
                      "value": "{{host}}",
                      "key": "host"
                    },
                    {
                      "description": {
                        "content": "",
                        "type": "text/plain"
                      },
                      "type": "any",
                      "value": "{{port}}",
                      "key": "port"
                    }
                  ]
                },
                "header": [
                  {
                    "description": {
                      "content": "Added as a part of security scheme: oauth2",
                      "type": "text/plain"
                    },
                    "key": "Authorization",
                    "value": "<token>"
                  },
                  {
                    "key": "Accept",
                    "value": "application/json"
                  }
                ],
                "method": "POST",
                "body": {
                  "mode": "raw",
                  "raw": "{\n  \"recipient\": \"<string>\",\n  \"senderId\": \"<string>\",\n  \"channel\": \"<string>\"\n}",
                  "options": {
                    "raw": {
                      "language": "json"
                    }
                  }
                }
              },
              "status": "OK",
              "code": 200,
              "header": [
                {
                  "key": "Content-Type",
                  "value": "application/json"
                }
              ],
              "body": "{\n  \"sessionToken\": \"<string>\",\n  \"status\": \"<string>\"\n}",
              "cookie": [],
              "_postman_previewlanguage": "json"
            },
            {
              "id": "84cce403-b0d4-4bf2-8b10-e124ede35c02",
              "name": "Bad Request: The request body is malformed or contains invalid data",
              "originalRequest": {
                "url": {
                  "path": [
                    "notification-senders",
                    "otp",
                    "send"
                  ],
                  "host": [
                    "{{baseUrl}}"
                  ],
                  "query": [],
                  "variable": [
                    {
                      "description": {
                        "content": "",
                        "type": "text/plain"
                      },
                      "type": "any",
                      "value": "{{host}}",
                      "key": "host"
                    },
                    {
                      "description": {
                        "content": "",
                        "type": "text/plain"
                      },
                      "type": "any",
                      "value": "{{port}}",
                      "key": "port"
                    }
                  ]
                },
                "header": [
                  {
                    "description": {
                      "content": "Added as a part of security scheme: oauth2",
                      "type": "text/plain"
                    },
                    "key": "Authorization",
                    "value": "<token>"
                  },
                  {
                    "key": "Accept",
                    "value": "application/json"
                  }
                ],
                "method": "POST",
                "body": {
                  "mode": "raw",
                  "raw": "{\n  \"recipient\": \"<string>\",\n  \"senderId\": \"<string>\",\n  \"channel\": \"<string>\"\n}",
                  "options": {
                    "raw": {
                      "language": "json"
                    }
                  }
                }
              },
              "status": "Bad Request",
              "code": 400,
              "header": [
                {
                  "key": "Content-Type",
                  "value": "application/json"
                }
              ],
              "body": "{\n  \"code\": \"<string>\",\n  \"message\": {\n    \"key\": \"<string>\",\n    \"defaultValue\": \"<string>\"\n  },\n  \"description\": {\n    \"key\": \"<string>\",\n    \"defaultValue\": \"<string>\"\n  }\n}",
              "cookie": [],
              "_postman_previewlanguage": "json"
            },
            {
              "id": "1a8db313-8e15-4348-961e-8c0234c5fa51",
              "name": "Not Found: The specified message notification sender does not exist",
              "originalRequest": {
                "url": {
                  "path": [
                    "notification-senders",
                    "otp",
                    "send"
                  ],
                  "host": [
                    "{{baseUrl}}"
                  ],
                  "query": [],
                  "variable": [
                    {
                      "description": {
                        "content": "",
                        "type": "text/plain"
                      },
                      "type": "any",
                      "value": "{{host}}",
                      "key": "host"
                    },
                    {
                      "description": {
                        "content": "",
                        "type": "text/plain"
                      },
                      "type": "any",
                      "value": "{{port}}",
                      "key": "port"
                    }
                  ]
                },
                "header": [
                  {
                    "description": {
                      "content": "Added as a part of security scheme: oauth2",
                      "type": "text/plain"
                    },
                    "key": "Authorization",
                    "value": "<token>"
                  },
                  {
                    "key": "Accept",
                    "value": "application/json"
                  }
                ],
                "method": "POST",
                "body": {
                  "mode": "raw",
                  "raw": "{\n  \"recipient\": \"<string>\",\n  \"senderId\": \"<string>\",\n  \"channel\": \"<string>\"\n}",
                  "options": {
                    "raw": {
                      "language": "json"
                    }
                  }
                }
              },
              "status": "Not Found",
              "code": 404,
              "header": [
                {
                  "key": "Content-Type",
                  "value": "application/json"
                }
              ],
              "body": "{\n  \"code\": \"<string>\",\n  \"message\": {\n    \"key\": \"<string>\",\n    \"defaultValue\": \"<string>\"\n  },\n  \"description\": {\n    \"key\": \"<string>\",\n    \"defaultValue\": \"<string>\"\n  }\n}",
              "cookie": [],
              "_postman_previewlanguage": "json"
            },
            {
              "id": "b502dc0a-e783-45b5-8695-f500475033be",
              "name": "Internal Server Error: An unexpected error occurred while processing the request",
              "originalRequest": {
                "url": {
                  "path": [
                    "notification-senders",
                    "otp",
                    "send"
                  ],
                  "host": [
                    "{{baseUrl}}"
                  ],
                  "query": [],
                  "variable": [
                    {
                      "description": {
                        "content": "",
                        "type": "text/plain"
                      },
                      "type": "any",
                      "value": "{{host}}",
                      "key": "host"
                    },
                    {
                      "description": {
                        "content": "",
                        "type": "text/plain"
                      },
                      "type": "any",
                      "value": "{{port}}",
                      "key": "port"
                    }
                  ]
                },
                "header": [
                  {
                    "description": {
                      "content": "Added as a part of security scheme: oauth2",
                      "type": "text/plain"
                    },
                    "key": "Authorization",
                    "value": "<token>"
                  },
                  {
                    "key": "Accept",
                    "value": "application/json"
                  }
                ],
                "method": "POST",
                "body": {
                  "mode": "raw",
                  "raw": "{\n  \"recipient\": \"<string>\",\n  \"senderId\": \"<string>\",\n  \"channel\": \"<string>\"\n}",
                  "options": {
                    "raw": {
                      "language": "json"
                    }
                  }
                }
              },
              "status": "Internal Server Error",
              "code": 500,
              "header": [
                {
                  "key": "Content-Type",
                  "value": "application/json"
                }
              ],
              "body": "{\n  \"code\": \"<string>\",\n  \"message\": {\n    \"key\": \"<string>\",\n    \"defaultValue\": \"<string>\"\n  },\n  \"description\": {\n    \"key\": \"<string>\",\n    \"defaultValue\": \"<string>\"\n  }\n}",
              "cookie": [],
              "_postman_previewlanguage": "json"
            }
          ],
          "event": [],
          "protocolProfileBehavior": {
            "disableBodyPruning": true
          }
        },
        {
          "id": "fa39e9bc-8e8a-4504-992b-2ec8e5598e6c",
          "name": "Verify a One Time Password (OTP)",
          "request": {
            "name": "Verify a One Time Password (OTP)",
            "description": {
              "content": "Verify a One Time Password (OTP) using the provided session token and OTP code.",
              "type": "text/plain"
            },
            "url": {
              "path": [
                "notification-senders",
                "otp",
                "verify"
              ],
              "host": [
                "{{baseUrl}}"
              ],
              "query": [],
              "variable": [
                {
                  "description": {
                    "content": "",
                    "type": "text/plain"
                  },
                  "type": "any",
                  "value": "{{host}}",
                  "key": "host"
                },
                {
                  "description": {
                    "content": "",
                    "type": "text/plain"
                  },
                  "type": "any",
                  "value": "{{port}}",
                  "key": "port"
                }
              ]
            },
            "header": [
              {
                "key": "Content-Type",
                "value": "application/json"
              },
              {
                "key": "Accept",
                "value": "application/json"
              }
            ],
            "method": "POST",
            "auth": null,
            "body": {
              "mode": "raw",
              "raw": "{\n  \"sessionToken\": \"<string>\",\n  \"otpCode\": \"<string>\"\n}",
              "options": {
                "raw": {
                  "language": "json"
                }
              }
            }
          },
          "response": [
            {
              "id": "e6939777-a764-48c5-9a15-31fb21753499",
              "name": "OTP verified successfully",
              "originalRequest": {
                "url": {
                  "path": [
                    "notification-senders",
                    "otp",
                    "verify"
                  ],
                  "host": [
                    "{{baseUrl}}"
                  ],
                  "query": [],
                  "variable": [
                    {
                      "description": {
                        "content": "",
                        "type": "text/plain"
                      },
                      "type": "any",
                      "value": "{{host}}",
                      "key": "host"
                    },
                    {
                      "description": {
                        "content": "",
                        "type": "text/plain"
                      },
                      "type": "any",
                      "value": "{{port}}",
                      "key": "port"
                    }
                  ]
                },
                "header": [
                  {
                    "description": {
                      "content": "Added as a part of security scheme: oauth2",
                      "type": "text/plain"
                    },
                    "key": "Authorization",
                    "value": "<token>"
                  },
                  {
                    "key": "Accept",
                    "value": "application/json"
                  }
                ],
                "method": "POST",
                "body": {
                  "mode": "raw",
                  "raw": "{\n  \"sessionToken\": \"<string>\",\n  \"otpCode\": \"<string>\"\n}",
                  "options": {
                    "raw": {
                      "language": "json"
                    }
                  }
                }
              },
              "status": "OK",
              "code": 200,
              "header": [
                {
                  "key": "Content-Type",
                  "value": "application/json"
                }
              ],
              "body": "{\n  \"status\": \"<string>\"\n}",
              "cookie": [],
              "_postman_previewlanguage": "json"
            },
            {
              "id": "1a6734e2-6d3d-48b9-9af1-a249448bb18f",
              "name": "Bad Request: The request body is malformed or the session token is invalid",
              "originalRequest": {
                "url": {
                  "path": [
                    "notification-senders",
                    "otp",
                    "verify"
                  ],
                  "host": [
                    "{{baseUrl}}"
                  ],
                  "query": [],
                  "variable": [
                    {
                      "description": {
                        "content": "",
                        "type": "text/plain"
                      },
                      "type": "any",
                      "value": "{{host}}",
                      "key": "host"
                    },
                    {
                      "description": {
                        "content": "",
                        "type": "text/plain"
                      },
                      "type": "any",
                      "value": "{{port}}",
                      "key": "port"
                    }
                  ]
                },
                "header": [
                  {
                    "description": {
                      "content": "Added as a part of security scheme: oauth2",
                      "type": "text/plain"
                    },
                    "key": "Authorization",
                    "value": "<token>"
                  },
                  {
                    "key": "Accept",
                    "value": "application/json"
                  }
                ],
                "method": "POST",
                "body": {
                  "mode": "raw",
                  "raw": "{\n  \"sessionToken\": \"<string>\",\n  \"otpCode\": \"<string>\"\n}",
                  "options": {
                    "raw": {
                      "language": "json"
                    }
                  }
                }
              },
              "status": "Bad Request",
              "code": 400,
              "header": [
                {
                  "key": "Content-Type",
                  "value": "application/json"
                }
              ],
              "body": "{\n  \"code\": \"<string>\",\n  \"message\": {\n    \"key\": \"<string>\",\n    \"defaultValue\": \"<string>\"\n  },\n  \"description\": {\n    \"key\": \"<string>\",\n    \"defaultValue\": \"<string>\"\n  }\n}",
              "cookie": [],
              "_postman_previewlanguage": "json"
            },
            {
              "id": "4c81f742-5025-4e31-875c-721fb2229950",
              "name": "Internal Server Error: An unexpected error occurred while processing the request",
              "originalRequest": {
                "url": {
                  "path": [
                    "notification-senders",
                    "otp",
                    "verify"
                  ],
                  "host": [
                    "{{baseUrl}}"
                  ],
                  "query": [],
                  "variable": [
                    {
                      "description": {
                        "content": "",
                        "type": "text/plain"
                      },
                      "type": "any",
                      "value": "{{host}}",
                      "key": "host"
                    },
                    {
                      "description": {
                        "content": "",
                        "type": "text/plain"
                      },
                      "type": "any",
                      "value": "{{port}}",
                      "key": "port"
                    }
                  ]
                },
                "header": [
                  {
                    "description": {
                      "content": "Added as a part of security scheme: oauth2",
                      "type": "text/plain"
                    },
                    "key": "Authorization",
                    "value": "<token>"
                  },
                  {
                    "key": "Accept",
                    "value": "application/json"
                  }
                ],
                "method": "POST",
                "body": {
                  "mode": "raw",
                  "raw": "{\n  \"sessionToken\": \"<string>\",\n  \"otpCode\": \"<string>\"\n}",
                  "options": {
                    "raw": {
                      "language": "json"
                    }
                  }
                }
              },
              "status": "Internal Server Error",
              "code": 500,
              "header": [
                {
                  "key": "Content-Type",
                  "value": "application/json"
                }
              ],
              "body": "{\n  \"code\": \"<string>\",\n  \"message\": {\n    \"key\": \"<string>\",\n    \"defaultValue\": \"<string>\"\n  },\n  \"description\": {\n    \"key\": \"<string>\",\n    \"defaultValue\": \"<string>\"\n  }\n}",
              "cookie": [],
              "_postman_previewlanguage": "json"
            }
          ],
          "event": [],
          "protocolProfileBehavior": {
            "disableBodyPruning": true
          }
        }
      ],
      "event": []
    }
  ],
  "event": [],
  "variable": [
    {
      "description": {
        "content": "",
        "type": "text/plain"
      },
      "type": "any",
      "value": "localhost",
      "key": "host"
    },
    {
      "description": {
        "content": "",
        "type": "text/plain"
      },
      "type": "any",
      "value": "8090",
      "key": "port"
    },
    {
      "type": "string",
      "value": "https://{{host}}:{{port}}",
      "key": "baseUrl"
    },
    {
      "key": "clientId",
      "value": "",
      "type": "string"
    },
    {
      "key": "clientSecret",
      "value": "",
      "type": "string"
    }
  ],
  "auth": {
    "type": "oauth2",
    "oauth2": [
      {
        "key": "grant_type",
        "value": "client_credentials"
      },
      {
        "key": "accessTokenUrl",
        "value": "{{baseUrl}}/oauth2/token"
      },
      {
        "key": "clientId",
        "value": "{{clientId}}"
      },
      {
        "key": "clientSecret",
        "value": "{{clientSecret}}"
      },
      {
        "key": "scope",
        "value": "system"
      },
      {
        "key": "addTokenTo",
        "value": "header"
      }
    ]
  },
  "info": {
    "_postman_id": "5276933a-9164-47f1-9ec1-8b6981e5cec9",
    "name": "Notification Sender API",
    "schema": "https://schema.getpostman.com/json/collection/v2.1.0/collection.json",
    "description": {
      "content": "Configure channels for sending OTP codes and notification messages to users. Supported providers include SMS gateways and email services.",
      "type": "text/plain"
    }
  }
}